WeiXueyuanGolangJiaochengFix1/README.md
WeiXueyuanGolangJiaochengFix1/__init__.py
WeiXueyuanGolangJiaochengFix1/__main__.py
WeiXueyuanGolangJiaochengFix1/file.epub
WeiXueyuanGolangJiaochengFix1/index.html
WeiXueyuanGolangJiaochengFix1/css/__init__.py
WeiXueyuanGolangJiaochengFix1/css/annotations.css
WeiXueyuanGolangJiaochengFix1/css/main.css
WeiXueyuanGolangJiaochengFix1/css/normalize.css
WeiXueyuanGolangJiaochengFix1/css/popup.css
WeiXueyuanGolangJiaochengFix1/font/__init__.py
WeiXueyuanGolangJiaochengFix1/font/fontello.eot
WeiXueyuanGolangJiaochengFix1/font/fontello.svg
WeiXueyuanGolangJiaochengFix1/font/fontello.ttf
WeiXueyuanGolangJiaochengFix1/font/fontello.woff
WeiXueyuanGolangJiaochengFix1/img/__init__.py
WeiXueyuanGolangJiaochengFix1/img/annotator-glyph-sprite.png
WeiXueyuanGolangJiaochengFix1/img/annotator-icon-sprite.png
WeiXueyuanGolangJiaochengFix1/img/apple-touch-icon.png
WeiXueyuanGolangJiaochengFix1/img/cancelfullscreen.png
WeiXueyuanGolangJiaochengFix1/img/close.png
WeiXueyuanGolangJiaochengFix1/img/fullscreen.png
WeiXueyuanGolangJiaochengFix1/img/loader.gif
WeiXueyuanGolangJiaochengFix1/img/menu-icon.png
WeiXueyuanGolangJiaochengFix1/img/save.png
WeiXueyuanGolangJiaochengFix1/img/saved.png
WeiXueyuanGolangJiaochengFix1/img/settings-s.png
WeiXueyuanGolangJiaochengFix1/img/settings.png
WeiXueyuanGolangJiaochengFix1/img/star.png
WeiXueyuanGolangJiaochengFix1/js/__init__.py
WeiXueyuanGolangJiaochengFix1/js/epub.js
WeiXueyuanGolangJiaochengFix1/js/epub.min.js
WeiXueyuanGolangJiaochengFix1/js/epub.min.map
WeiXueyuanGolangJiaochengFix1/js/hooks.min.js
WeiXueyuanGolangJiaochengFix1/js/hooks.min.map
WeiXueyuanGolangJiaochengFix1/js/reader.js
WeiXueyuanGolangJiaochengFix1/js/reader.js.map
WeiXueyuanGolangJiaochengFix1/js/reader.min.js
WeiXueyuanGolangJiaochengFix1/js/reader.min.map
WeiXueyuanGolangJiaochengFix1/js/hooks/__init__.py
WeiXueyuanGolangJiaochengFix1/js/hooks/extensions/__init__.py
WeiXueyuanGolangJiaochengFix1/js/hooks/extensions/highlight.js
wei_xueyuan_golang_jiaocheng_fix1-2025.3.25.0.dist-info/METADATA
wei_xueyuan_golang_jiaocheng_fix1-2025.3.25.0.dist-info/WHEEL
wei_xueyuan_golang_jiaocheng_fix1-2025.3.25.0.dist-info/entry_points.txt
wei_xueyuan_golang_jiaocheng_fix1-2025.3.25.0.dist-info/top_level.txt
wei_xueyuan_golang_jiaocheng_fix1-2025.3.25.0.dist-info/RECORD
